__init__.py
cv_ae_multi_model/multi_model_module.py
cv_ae_multi_model-0.0.1.dist-info/LICENSE
cv_ae_multi_model-0.0.1.dist-info/METADATA
cv_ae_multi_model-0.0.1.dist-info/WHEEL
cv_ae_multi_model-0.0.1.dist-info/top_level.txt
cv_ae_multi_model-0.0.1.dist-info/RECORD
